bq/__init__.py
bq/module_engine/__init__.py
bq/module_engine/setup/module_setup.py
bq/module_engine/setup/__init__.py
bq/module_engine/setup/scaffolds/__init__.py
bq/module_engine/setup/scaffolds/matlab_module/+package+/+package+.xml_tmpl
bq/module_engine/setup/scaffolds/matlab_module/+package+/runtime-module.cfg_tmpl
bq/module_engine/setup/scaffolds/matlab_module/+package+/+package+.m_tmpl
bq/module_engine/setup/scaffolds/matlab_module/+package+/setup.py_tmpl
bq/module_engine/setup/scaffolds/matlab_module/+package+/public/help.html
bq/module_engine/setup/scaffolds/matlab_module/+package+/public/thumbnail.png
bq/module_engine/setup/scaffolds/matlab_module/+package+/+bq/urlread.m
bq/module_engine/setup/scaffolds/matlab_module/+package+/+bq/connect.m
bq/module_engine/setup/scaffolds/matlab_module/+package+/+bq/xml2str.m
bq/module_engine/setup/scaffolds/matlab_module/+package+/+bq/str2xml.m
bq/module_engine/setup/scaffolds/matlab_module/+package+/+bq/delete.m
bq/module_engine/setup/scaffolds/matlab_module/+package+/+bq/get.m
bq/module_engine/setup/scaffolds/matlab_module/+package+/+bq/urlwrite.m
bq/module_engine/setup/scaffolds/matlab_module/+package+/+bq/get_xml.m
bq/module_engine/setup/scaffolds/matlab_module/+package+/+bq/post_mpform.m
bq/module_engine/setup/scaffolds/matlab_module/+package+/+bq/put.m
bq/module_engine/setup/scaffolds/matlab_module/+package+/+bq/imread.m
bq/module_engine/setup/scaffolds/matlab_module/+package+/+bq/imreadND.m
bq/module_engine/setup/scaffolds/matlab_module/+package+/+bq/parsetags.m
bq/module_engine/setup/scaffolds/matlab_module/+package+/+bq/iminfo.m
bq/module_engine/setup/scaffolds/matlab_module/+package+/+bq/post.m
bq/module_engine/setup/scaffolds/matlab_module/+package+/+bq/@Gobject/Gobject.m
bq/module_engine/setup/scaffolds/matlab_module/+package+/+bq/@Factory/Factory.m
bq/module_engine/setup/scaffolds/matlab_module/+package+/+bq/@File/File.m
bisque_engine-0.6a9.dist-info/entry_points.txt
bisque_engine-0.6a9.dist-info/top_level.txt
bisque_engine-0.6a9.dist-info/WHEEL
bisque_engine-0.6a9.dist-info/DESCRIPTION.rst
bisque_engine-0.6a9.dist-info/RECORD
bisque_engine-0.6a9.dist-info/METADATA
bisque_engine-0.6a9.dist-info/metadata.json
