Metadata-Version: 2.0
Name: bisque-engine
Version: 0.6a9
Summary: The BisQue module engine: build add-on modules for BisQue
Home-page: http://biodev.ece.ucsb.edu/project/bisque
Author: Center for BioImage Informatics
Author-email: bisque-bioimage@googlegroups.com
License: UNKNOWN
Keywords: database image processing scientific
Platform: UNKNOWN
Classifier: Programming Language :: Python
Classifier: Framework :: Pyramid
Classifier: Topic :: Internet :: WWW/HTTP
Classifier: Topic :: Internet :: WWW/HTTP :: WSGI :: Application
Requires-Dist: bisque-api
Requires-Dist: bisque-base
Provides-Extra: lxml
Requires-Dist: lxml; extra == 'lxml'
